socket_dll/__init__.py
socket_dll/wrapper.py
socket_dll/bin/SocketDll.dll
socket_dll_srchoi-0.1.1.dist-info/licenses/LICENSE
socket_dll_srchoi-0.1.1.dist-info/METADATA
socket_dll_srchoi-0.1.1.dist-info/WHEEL
socket_dll_srchoi-0.1.1.dist-info/top_level.txt
socket_dll_srchoi-0.1.1.dist-info/RECORD
