Metadata-Version: 2.4
Name: socket-dll-srchoi
Version: 0.1.1
Summary: 고성능 C++ 소켓 라이브러리를 위한 Python 래퍼
Home-page: https://github.com/srchoi/socket-dll
Author: srchoi
Author-email: srchoi@example.com
Project-URL: Bug Reports, https://github.com/srchoi/socket-dll/issues
Project-URL: Source, https://github.com/srchoi/socket-dll
Keywords: socket tcp networking dll c++
Classifier: Programming Language :: Python :: 3
Classifier: Programming Language :: Python :: 3.7
Classifier: Programming Language :: Python :: 3.8
Classifier: Programming Language :: Python :: 3.9
Classifier: Programming Language :: Python :: 3.10
Classifier: Programming Language :: Python :: 3.11
Classifier: Programming Language :: Python :: 3.12
Classifier: Programming Language :: Python :: 3.13
Classifier: License :: OSI Approved :: MIT License
Classifier: Operating System :: Microsoft :: Windows
Classifier: Development Status :: 3 - Alpha
Classifier: Intended Audience :: Developers
Classifier: Topic :: Software Development :: Libraries :: Python Modules
Classifier: Topic :: System :: Networking
Requires-Python: >=3.7
License-File: LICENSE
Dynamic: author
Dynamic: author-email
Dynamic: classifier
Dynamic: description
Dynamic: description-content-type
Dynamic: home-page
Dynamic: keywords
Dynamic: license-file
Dynamic: project-url
Dynamic: requires-python
Dynamic: summary
